LearnBasics/ALU_top/Ripple_Borrow_Subtractor/Full_Subtractor.v
module Full_Subtractor (
    input a,
    input b,
    input B,
    output Bout,
    output D
);

    assign D = a ^ b ^ B;
    assign Bout = (~a & b) | (~(a ^ b) & B);
    
endmodule

LearnBasics/ALU_top/Ripple_Borrow_Subtractor/RBS.v
module RBS (
    input [3:0] a,
    input [3:0] b, 
    output Bout,
    output [3:0] D
);

    wire [4:0] B;
    assign B[0] = 1'b0;

    Full_Subtractor F0 (
        .a(a[0]),
        .b(b[0]),
        .B(B[0]),
        .Bout(B[1]),
        .D(D[0])
    );

    Full_Subtractor F1 (
        .a(a[1]),
        .b(b[1]),
        .B(B[1]),
        .Bout(B[2]),
        .D(D[1])
    );

    Full_Subtractor F2 (
        .a(a[2]),
        .b(b[2]),
        .B(B[2]),
        .Bout(B[3]),
        .D(D[2])
    );
    
    Full_Subtractor F3 (
        .a(a[3]),
        .b(b[3]),
        .B(B[3]),
        .Bout(B[4]),
        .D(D[3])
    );

    assign Bout = B[4];

endmodule

LearnBasics/ALU_top/Ripple_Borrow_Subtractor/tb_RBS.v
`timescale 1ns/1ps
module tb_RBS;

    reg [3:0] a;
    reg [3:0] b;
    wire [3:0] D;
    wire Bout;

    RBS uut(
        .a(a),
        .b(b),
        .D(D),
        .Bout(Bout)
    );

    initial begin
        $dumpfile("wave.vcd");
        $dumpvars(0, tb_RBS);
    end

    integer i, j;
    initial begin
        $monitor("Time=%0t a=%b b=%b D=%b Bout=%b",
                    $time, a, b, D, Bout);
            for (i = 0; i < 16; i= i + 1) begin
                for (j = 0; j < 16; j = j + 1) begin
                    a = i;
                    b = j;
                    #10;
                end
            end

        $finish;
    end

endmodule

LearnBasics/ALU_top/Ripple_Borrow_Subtractor/wave.vcd
$date
	Wed Jul 29 17:55:38 2026
$end
$version
	Icarus Verilog
$end
$timescale
	1ps
$end
$scope module tb_RBS $end
$var wire 4 ! D [3:0] $end
$var wire 1 " Bout $end
$var reg 4 # a [3:0] $end
$var reg 4 $ b [3:0] $end
$var integer 32 % i [31:0] $end
$var integer 32 & j [31:0] $end
$scope module uut $end
$var wire 4 ' a [3:0] $end
$var wire 4 ( b [3:0] $end
$var wire 4 ) D [3:0] $end
$var wire 1 " Bout $end
$var wire 5 * B [4:0] $end
$scope module F0 $end
$var wire 1 + B $end
$var wire 1 , Bout $end
$var wire 1 - D $end
$var wire 1 . a $end
$var wire 1 / b $end
$upscope $end
$scope module F1 $end
$var wire 1 0 B $end
$var wire 1 1 Bout $end
$var wire 1 2 D $end
$var wire 1 3 a $end
$var wire 1 4 b $end
$upscope $end
$scope module F2 $end
$var wire 1 5 B $end
$var wire 1 6 Bout $end
$var wire 1 7 D $end
$var wire 1 8 a $end
$var wire 1 9 b $end
$upscope $end
$scope module F3 $end
$var wire 1 : B $end
$var wire 1 ; Bout $end
$var wire 1 < D $end
$var wire 1 = a $end
$var wire 1 > b $end
$upscope $end
$upscope $end
$upscope $end
$enddefinitions $end
#0
$dumpvars
0>
0=
0<
0;
0:
09
08
07
06
05
04
03
02
01
00
0/
0.
0-
0,
0+
b0 *
b0 )
b0 (
b0 '
b0 &
b0 %
b0 $
b0 #
0"
b0 !
$end
#10000
1"
1;
1<
1:
16
17
15
11
12
10
b1111 !
b1111 )
1-
b11110 *
1,
1/
b1 $
b1 (
b1 &
#20000
00
0-
b11100 *
0,
b1110 !
b1110 )
12
0/
14
b10 $
b10 (
b10 &
#30000
02
10
b1101 !
b1101 )
1-
b11110 *
1,
1/
b11 $
b11 (
b11 &
#40000
00
05
0-
0,
02
b11000 *
01
b1100 !
b1100 )
17
0/
04
19
b100 $
b100 (
b100 &
#50000
07
15
11
12
10
b1011 !
b1011 )
1-
b11110 *
1,
1/
b101 $
b101 (
b101 &
#60000
00
0-
b11100 *
0,
b1010 !
b1010 )
12
0/
14
b110 $
b110 (
b110 &
#70000
02
10
b1001 !
b1001 )
1-
b11110 *
1,
1/
b111 $
b111 (
b111 &
#80000
00
05
0:
0-
0,
02
01
07
b10000 *
06
b1000 !
b1000 )
1<
0/
04
09
1>
b1000 $
b1000 (
b1000 &
#90000
0<
1:
16
17
15
11
12
10
b111 !
b111 )
1-
b11110 *
1,
1/
b1001 $
b1001 (
b1001 &
#100000
00
0-
b11100 *
0,
b110 !
b110 )
12
0/
14
b1010 $
b1010 (
b1010 &
#110000
02
10
b101 !
b101 )
1-
b11110 *
1,
1/
b1011 $
b1011 (
b1011 &
#120000
00
05
0-
0,
02
b11000 *
01
b100 !
b100 )
17
0/
04
19
b1100 $
b1100 (
b1100 &
#130000
07
15
11
12
10
b11 !
b11 )
1-
b11110 *
1,
1/
b1101 $
b1101 (
b1101 &
#140000
00
0-
b11100 *
0,
b10 !
b10 )
12
0/
14
b1110 $
b1110 (
b1110 &
#150000
02
10
b1 !
b1 )
1-
b11110 *
1,
1/
b1111 $
b1111 (
b1111 &
#160000
00
05
0:
0"
0,
02
01
07
06
b1 !
b1 )
0<
b0 *
0;
0/
04
09
0>
1.
b0 $
b0 (
b1 #
b1 '
b1 %
b0 &
#170000
b0 !
b0 )
0-
1/
b1 $
b1 (
b1 &
#180000
1"
1;
1<
1:
16
17
15
1-
b1111 !
b1111 )
12
b11100 *
11
0/
14
b10 $
b10 (
b10 &
#190000
b1110 !
b1110 )
0-
1/
b11 $
b11 (
b11 &
#200000
05
1-
02
b11000 *
01
b1101 !
b1101 )
17
0/
04
19
b100 $
b100 (
b100 &
#210000
b1100 !
b1100 )
0-
1/
b101 $
b101 (
b101 &
#220000
07
15
1-
b1011 !
b1011 )
12
b11100 *
11
0/
14
b110 $
b110 (
b110 &
#230000
b1010 !
b1010 )
0-
1/
b111 $
b111 (
b111 &
#240000
05
0:
1-
02
01
07
b10000 *
06
b1001 !
b1001 )
1<
0/
04
09
1>
b1000 $
b1000 (
b1000 &
#250000
b1000 !
b1000 )
0-
1/
b1001 $
b1001 (
b1001 &
#260000
0<
1:
16
17
15
1-
b111 !
b111 )
12
b11100 *
11
0/
14
b1010 $
b1010 (
b1010 &
#270000
b110 !
b110 )
0-
1/
b1011 $
b1011 (
b1011 &
#280000
05
1-
02
b11000 *
01
b101 !
b101 )
17
0/
04
19
b1100 $
b1100 (
b1100 &
#290000
b100 !
b100 )
0-
1/
b1101 $
b1101 (
b1101 &
#300000
07
15
1-
b11 !
b11 )
12
b11100 *
11
0/
14
b1110 $
b1110 (
b1110 &
#310000
b10 !
b10 )
0-
1/
b1111 $
b1111 (
b1111 &
#320000
05
0:
0"
01
07
06
b10 !
b10 )
0<
b0 *
0;
0/
04
09
0>
0.
13
b0 $
b0 (
b10 #
b10 '
b10 %
b0 &
#330000
02
10
b1 !
b1 )
1-
b10 *
1,
1/
b1 $
b1 (
b1 &
#340000
0"
0;
0<
0:
06
07
05
01
00
0-
b0 *
0,
b0 !
b0 )
02
0/
14
b10 $
b10 (
b10 &
#350000
1"
1;
1<
1:
16
17
15
11
12
10
b1111 !
b1111 )
1-
b11110 *
1,
1/
b11 $
b11 (
b11 &
#360000
05
01
00
0-
b11000 *
0,
12
b1110 !
b1110 )
17
0/
04
19
b100 $
b100 (
b100 &
#370000
02
10
b1101 !
b1101 )
1-
b11010 *
1,
1/
b101 $
b101 (
b101 &
#380000
17
05
01
00
0-
b11000 *
0,
b1100 !
b1100 )
02
0/
14
b110 $
b110 (
b110 &
#390000
07
15
11
12
10
b1011 !
b1011 )
1-
b11110 *
1,
1/
b111 $
b111 (
b111 &
#400000
05
01
00
0:
0-
0,
12
07
b10000 *
06
b1010 !
b1010 )
1<
0/
04
09
1>
b1000 $
b1000 (
b1000 &
#410000
02
10
b1001 !
b1001 )
1-
b10010 *
1,
1/
b1001 $
b1001 (
b1001 &
#420000
1<
0:
06
07
05
01
00
0-
b10000 *
0,
b1000 !
b1000 )
02
0/
14
b1010 $
b1010 (
b1010 &
#430000
0<
1:
16
17
15
11
12
10
b111 !
b111 )
1-
b11110 *
1,
1/
b1011 $
b1011 (
b1011 &
#440000
05
01
00
0-
b11000 *
0,
12
b110 !
b110 )
17
0/
04
19
b1100 $
b1100 (
b1100 &
#450000
02
10
b101 !
b101 )
1-
b11010 *
1,
1/
b1101 $
b1101 (
b1101 &
#460000
17
05
01
00
0-
b11000 *
0,
b100 !
b100 )
02
0/
14
b1110 $
b1110 (
b1110 &
#470000
07
15
11
12
10
b11 !
b11 )
1-
b11110 *
1,
1/
b1111 $
b1111 (
b1111 &
#480000
05
01
00
0:
0"
0,
12
07
06
b11 !
b11 )
0<
b0 *
0;
0/
04
09
0>
1.
b0 $
b0 (
b11 #
b11 '
b11 %
b0 &
#490000
b10 !
b10 )
0-
1/
b1 $
b1 (
b1 &
#500000
1-
b1 !
b1 )
02
0/
14
b10 $
b10 (
b10 &
#510000
b0 !
b0 )
0-
1/
b11 $
b11 (
b11 &
#520000
1"
1;
1<
1:
1-
12
b1111 !
b1111 )
17
b11000 *
16
0/
04
19
b100 $
b100 (
b100 &
#530000
b1110 !
b1110 )
0-
1/
b101 $
b101 (
b101 &
#540000
1-
b1101 !
b1101 )
02
0/
14
b110 $
b110 (
b110 &
#550000
b1100 !
b1100 )
0-
1/
b111 $
b111 (
b111 &
#560000
0:
1-
12
07
b10000 *
06
b1011 !
b1011 )
1<
0/
04
09
1>
b1000 $
b1000 (
b1000 &
#570000
b1010 !
b1010 )
0-
1/
b1001 $
b1001 (
b1001 &
#580000
1-
b1001 !
b1001 )
02
0/
14
b1010 $
b1010 (
b1010 &
#590000
b1000 !
b1000 )
0-
1/
b1011 $
b1011 (
b1011 &
#600000
0<
1:
1-
12
b111 !
b111 )
17
b11000 *
16
0/
04
19
b1100 $
b1100 (
b1100 &
#610000
b110 !
b110 )
0-
1/
b1101 $
b1101 (
b1101 &
#620000
1-
b101 !
b101 )
02
0/
14
b1110 $
b1110 (
b1110 &
#630000
b100 !
b100 )
0-
1/
b1111 $
b1111 (
b1111 &
#640000
0:
0"
06
b100 !
b100 )
0<
b0 *
0;
0/
04
09
0>
0.
03
18
b0 $
b0 (
b100 #
b100 '
b100 %
b0 &
#650000
07
15
11
12
10
b11 !
b11 )
1-
b110 *
1,
1/
b1 $
b1 (
b1 &
#660000
00
0-
b100 *
0,
b10 !
b10 )
12
0/
14
b10 $
b10 (
b10 &
#670000
02
10
b1 !
b1 )
1-
b110 *
1,
1/
b11 $
b11 (
b11 &
#680000
0"
0;
0<
0:
06
00
05
0-
0,
02
b0 *
01
b0 !
b0 )
07
0/
04
19
b100 $
b100 (
b100 &
#690000
1"
1;
1<
1:
16
17
15
11
12
10
b1111 !
b1111 )
1-
b11110 *
1,
1/
b101 $
b101 (
b101 &
#700000
00
0-
b11100 *
0,
b1110 !
b1110 )
12
0/
14
b110 $
b110 (
b110 &
#710000
02
10
b1101 !
b1101 )
1-
b11110 *
1,
1/
b111 $
b111 (
b111 &
#720000
0:
06
00
05
0-
0,
02
b10000 *
01
17
b1100 !
b1100 )
1<
0/
04
09
1>
b1000 $
b1000 (
b1000 &
#730000
07
15
11
12
10
b1011 !
b1011 )
1-
b10110 *
1,
1/
b1001 $
b1001 (
b1001 &
#740000
00
0-
b10100 *
0,
b1010 !
b1010 )
12
0/
14
b1010 $
b1010 (
b1010 &
#750000
02
10
b1001 !
b1001 )
1-
b10110 *
1,
1/
b1011 $
b1011 (
b1011 &
#760000
1<
0:
06
00
05
0-
0,
02
b10000 *
01
b1000 !
b1000 )
07
0/
04
19
b1100 $
b1100 (
b1100 &
#770000
0<
1:
16
17
15
11
12
10
b111 !
b111 )
1-
b11110 *
1,
1/
b1101 $
b1101 (
b1101 &
#780000
00
0-
b11100 *
0,
b110 !
b110 )
12
0/
14
b1110 $
b1110 (
b1110 &
#790000
02
10
b101 !
b101 )
1-
b11110 *
1,
1/
b1111 $
b1111 (
b1111 &
#800000
0:
06
00
05
0"
0,
02
01
17
b101 !
b101 )
0<
b0 *
0;
0/
04
09
0>
1.
b0 $
b0 (
b101 #
b101 '
b101 %
b0 &
#810000
b100 !
b100 )
0-
1/
b1 $
b1 (
b1 &
#820000
07
15
1-
b11 !
b11 )
12
b100 *
11
0/
14
b10 $
b10 (
b10 &
#830000
b10 !
b10 )
0-
1/
b11 $
b11 (
b11 &
#840000
0"
0;
0<
0:
06
05
1-
02
b0 *
01
b1 !
b1 )
07
0/
04
19
b100 $
b100 (
b100 &
#850000
b0 !
b0 )
0-
1/
b101 $
b101 (
b101 &
#860000
1"
1;
1<
1:
16
17
15
1-
b1111 !
b1111 )
12
b11100 *
11
0/
14
b110 $
b110 (
b110 &
#870000
b1110 !
b1110 )
0-
1/
b111 $
b111 (
b111 &
#880000
0:
06
05
1-
02
b10000 *
01
17
b1101 !
b1101 )
1<
0/
04
09
1>
b1000 $
b1000 (
b1000 &
#890000
b1100 !
b1100 )
0-
1/
b1001 $
b1001 (
b1001 &
#900000
07
15
1-
b1011 !
b1011 )
12
b10100 *
11
0/
14
b1010 $
b1010 (
b1010 &
#910000
b1010 !
b1010 )
0-
1/
b1011 $
b1011 (
b1011 &
#920000
1<
0:
06
05
1-
02
b10000 *
01
b1001 !
b1001 )
07
0/
04
19
b1100 $
b1100 (
b1100 &
#930000
b1000 !
b1000 )
0-
1/
b1101 $
b1101 (
b1101 &
#940000
0<
1:
16
17
15
1-
b111 !
b111 )
12
b11100 *
11
0/
14
b1110 $
b1110 (
b1110 &
#950000
b110 !
b110 )
0-
1/
b1111 $
b1111 (
b1111 &
#960000
0:
06
05
0"
01
17
b110 !
b110 )
0<
b0 *
0;
0/
04
09
0>
0.
13
b0 $
b0 (
b110 #
b110 '
b110 %
b0 &
#970000
02
10
b101 !
b101 )
1-
b10 *
1,
1/
b1 $
b1 (
b1 &
#980000
17
05
01
00
0-
b0 *
0,
b100 !
b100 )
02
0/
14
b10 $
b10 (
b10 &
#990000
07
15
11
12
10
b11 !
b11 )
1-
b110 *
1,
1/
b11 $
b11 (
b11 &
#1000000
0"
0;
0<
05
0:
01
06
00
0-
b0 *
0,
12
b10 !
b10 )
07
0/
04
19
b100 $
b100 (
b100 &
#1010000
02
10
b1 !
b1 )
1-
b10 *
1,
1/
b101 $
b101 (
b101 &
#1020000
0"
0;
0<
0:
06
07
05
01
00
0-
b0 *
0,
b0 !
b0 )
02
0/
14
b110 $
b110 (
b110 &
#1030000
1"
1;
1<
1:
16
17
15
11
12
10
b1111 !
b1111 )
1-
b11110 *
1,
1/
b111 $
b111 (
b111 &
#1040000
05
0:
01
06
00
0-
b10000 *
0,
12
17
b1110 !
b1110 )
1<
0/
04
09
1>
b1000 $
b1000 (
b1000 &
#1050000
02
10
b1101 !
b1101 )
1-
b10010 *
1,
1/
b1001 $
b1001 (
b1001 &
#1060000
17
05
01
00
0-
b10000 *
0,
b1100 !
b1100 )
02
0/
14
b1010 $
b1010 (
b1010 &
#1070000
07
15
11
12
10
b1011 !
b1011 )
1-
b10110 *
1,
1/
b1011 $
b1011 (
b1011 &
#1080000
1<
05
0:
01
06
00
0-
b10000 *
0,
12
b1010 !
b1010 )
07
0/
04
19
b1100 $
b1100 (
b1100 &
#1090000
02
10
b1001 !
b1001 )
1-
b10010 *
1,
1/
b1101 $
b1101 (
b1101 &
#1100000
1<
0:
06
07
05
01
00
0-
b10000 *
0,
b1000 !
b1000 )
02
0/
14
b1110 $
b1110 (
b1110 &
#1110000
0<
1:
16
17
15
11
12
10
b111 !
b111 )
1-
b11110 *
1,
1/
b1111 $
b1111 (
b1111 &
#1120000
05
0:
01
06
00
0"
0,
12
17
b111 !
b111 )
0<
b0 *
0;
0/
04
09
0>
1.
b0 $
b0 (
b111 #
b111 '
b111 %
b0 &
#1130000
b110 !
b110 )
0-
1/
b1 $
b1 (
b1 &
#1140000
1-
b101 !
b101 )
02
0/
14
b10 $
b10 (
b10 &
#1150000
b100 !
b100 )
0-
1/
b11 $
b11 (
b11 &
#1160000
1-
12
b11 !
b11 )
07
0/
04
19
b100 $
b100 (
b100 &
#1170000
b10 !
b10 )
0-
1/
b101 $
b101 (
b101 &
#1180000
1-
b1 !
b1 )
02
0/
14
b110 $
b110 (
b110 &
#1190000
b0 !
b0 )
0-
1/
b111 $
b111 (
b111 &
#1200000
1"
1-
12
17
b1111 !
b1111 )
1<
b10000 *
1;
0/
04
09
1>
b1000 $
b1000 (
b1000 &
#1210000
b1110 !
b1110 )
0-
1/
b1001 $
b1001 (
b1001 &
#1220000
1-
b1101 !
b1101 )
02
0/
14
b1010 $
b1010 (
b1010 &
#1230000
b1100 !
b1100 )
0-
1/
b1011 $
b1011 (
b1011 &
#1240000
1-
12
b1011 !
b1011 )
07
0/
04
19
b1100 $
b1100 (
b1100 &
#1250000
b1010 !
b1010 )
0-
1/
b1101 $
b1101 (
b1101 &
#1260000
1-
b1001 !
b1001 )
02
0/
14
b1110 $
b1110 (
b1110 &
#1270000
b1000 !
b1000 )
0-
1/
b1111 $
b1111 (
b1111 &
#1280000
0"
b0 *
0;
0/
04
09
0>
0.
03
08
1=
b0 $
b0 (
b1000 #
b1000 '
b1000 %
b0 &
#1290000
0<
1:
16
17
15
11
12
10
b111 !
b111 )
1-
b1110 *
1,
1/
b1 $
b1 (
b1 &
#1300000
00
0-
b1100 *
0,
b110 !
b110 )
12
0/
14
b10 $
b10 (
b10 &
#1310000
02
10
b101 !
b101 )
1-
b1110 *
1,
1/
b11 $
b11 (
b11 &
#1320000
00
05
0-
0,
02
b1000 *
01
b100 !
b100 )
17
0/
04
19
b100 $
b100 (
b100 &
#1330000
07
15
11
12
10
b11 !
b11 )
1-
b1110 *
1,
1/
b101 $
b101 (
b101 &
#1340000
00
0-
b1100 *
0,
b10 !
b10 )
12
0/
14
b110 $
b110 (
b110 &
#1350000
02
10
b1 !
b1 )
1-
b1110 *
1,
1/
b111 $
b111 (
b111 &
#1360000
0"
0;
00
05
0:
0-
0,
02
01
07
b0 *
06
b0 !
b0 )
0<
0/
04
09
1>
b1000 $
b1000 (
b1000 &
#1370000
1"
1;
1<
1:
16
17
15
11
12
10
b1111 !
b1111 )
1-
b11110 *
1,
1/
b1001 $
b1001 (
b1001 &
#1380000
00
0-
b11100 *
0,
b1110 !
b1110 )
12
0/
14
b1010 $
b1010 (
b1010 &
#1390000
02
10
b1101 !
b1101 )
1-
b11110 *
1,
1/
b1011 $
b1011 (
b1011 &
#1400000
00
05
0-
0,
02
b11000 *
01
b1100 !
b1100 )
17
0/
04
19
b1100 $
b1100 (
b1100 &
#1410000
07
15
11
12
10
b1011 !
b1011 )
1-
b11110 *
1,
1/
b1101 $
b1101 (
b1101 &
#1420000
00
0-
b11100 *
0,
b1010 !
b1010 )
12
0/
14
b1110 $
b1110 (
b1110 &
#1430000
02
10
b1001 !
b1001 )
1-
b11110 *
1,
1/
b1111 $
b1111 (
b1111 &
#1440000
0"
0;
00
05
0:
0,
02
01
07
b0 *
06
b1001 !
b1001 )
1<
0/
04
09
0>
1.
b0 $
b0 (
b1001 #
b1001 '
b1001 %
b0 &
#1450000
b1000 !
b1000 )
0-
1/
b1 $
b1 (
b1 &
#1460000
0<
1:
16
17
15
1-
b111 !
b111 )
12
b1100 *
11
0/
14
b10 $
b10 (
b10 &
#1470000
b110 !
b110 )
0-
1/
b11 $
b11 (
b11 &
#1480000
05
1-
02
b1000 *
01
b101 !
b101 )
17
0/
04
19
b100 $
b100 (
b100 &
#1490000
b100 !
b100 )
0-
1/
b101 $
b101 (
b101 &
#1500000
07
15
1-
b11 !
b11 )
12
b1100 *
11
0/
14
b110 $
b110 (
b110 &
#1510000
b10 !
b10 )
0-
1/
b111 $
b111 (
b111 &
#1520000
0"
0;
05
0:
1-
02
01
07
b0 *
06
b1 !
b1 )
0<
0/
04
09
1>
b1000 $
b1000 (
b1000 &
#1530000
b0 !
b0 )
0-
1/
b1001 $
b1001 (
b1001 &
#1540000
1"
1;
1<
1:
16
17
15
1-
b1111 !
b1111 )
12
b11100 *
11
0/
14
b1010 $
b1010 (
b1010 &
#1550000
b1110 !
b1110 )
0-
1/
b1011 $
b1011 (
b1011 &
#1560000
05
1-
02
b11000 *
01
b1101 !
b1101 )
17
0/
04
19
b1100 $
b1100 (
b1100 &
#1570000
b1100 !
b1100 )
0-
1/
b1101 $
b1101 (
b1101 &
#1580000
07
15
1-
b1011 !
b1011 )
12
b11100 *
11
0/
14
b1110 $
b1110 (
b1110 &
#1590000
b1010 !
b1010 )
0-
1/
b1111 $
b1111 (
b1111 &
#1600000
0"
0;
05
0:
01
07
b0 *
06
b1010 !
b1010 )
1<
0/
04
09
0>
0.
13
b0 $
b0 (
b1010 #
b1010 '
b1010 %
b0 &
#1610000
02
10
b1001 !
b1001 )
1-
b10 *
1,
1/
b1 $
b1 (
b1 &
#1620000
1<
0:
06
07
05
01
00
0-
b0 *
0,
b1000 !
b1000 )
02
0/
14
b10 $
b10 (
b10 &
#1630000
0<
1:
16
17
15
11
12
10
b111 !
b111 )
1-
b1110 *
1,
1/
b11 $
b11 (
b11 &
#1640000
05
01
00
0-
b1000 *
0,
12
b110 !
b110 )
17
0/
04
19
b100 $
b100 (
b100 &
#1650000
02
10
b101 !
b101 )
1-
b1010 *
1,
1/
b101 $
b101 (
b101 &
#1660000
17
05
01
00
0-
b1000 *
0,
b100 !
b100 )
02
0/
14
b110 $
b110 (
b110 &
#1670000
07
15
11
12
10
b11 !
b11 )
1-
b1110 *
1,
1/
b111 $
b111 (
b111 &
#1680000
05
0"
01
0;
00
0:
0-
0,
12
07
b0 *
06
b10 !
b10 )
0<
0/
04
09
1>
b1000 $
b1000 (
b1000 &
#1690000
02
10
b1 !
b1 )
1-
b10 *
1,
1/
b1001 $
b1001 (
b1001 &
#1700000
0"
0;
0<
0:
06
07
05
01
00
0-
b0 *
0,
b0 !
b0 )
02
0/
14
b1010 $
b1010 (
b1010 &
#1710000
1"
1;
1<
1:
16
17
15
11
12
10
b1111 !
b1111 )
1-
b11110 *
1,
1/
b1011 $
b1011 (
b1011 &
#1720000
05
01
00
0-
b11000 *
0,
12
b1110 !
b1110 )
17
0/
04
19
b1100 $
b1100 (
b1100 &
#1730000
02
10
b1101 !
b1101 )
1-
b11010 *
1,
1/
b1101 $
b1101 (
b1101 &
#1740000
17
05
01
00
0-
b11000 *
0,
b1100 !
b1100 )
02
0/
14
b1110 $
b1110 (
b1110 &
#1750000
07
15
11
12
10
b1011 !
b1011 )
1-
b11110 *
1,
1/
b1111 $
b1111 (
b1111 &
#1760000
05
0"
01
0;
00
0:
0,
12
07
b0 *
06
b1011 !
b1011 )
1<
0/
04
09
0>
1.
b0 $
b0 (
b1011 #
b1011 '
b1011 %
b0 &
#1770000
b1010 !
b1010 )
0-
1/
b1 $
b1 (
b1 &
#1780000
1-
b1001 !
b1001 )
02
0/
14
b10 $
b10 (
b10 &
#1790000
b1000 !
b1000 )
0-
1/
b11 $
b11 (
b11 &
#1800000
0<
1:
1-
12
b111 !
b111 )
17
b1000 *
16
0/
04
19
b100 $
b100 (
b100 &
#1810000
b110 !
b110 )
0-
1/
b101 $
b101 (
b101 &
#1820000
1-
b101 !
b101 )
02
0/
14
b110 $
b110 (
b110 &
#1830000
b100 !
b100 )
0-
1/
b111 $
b111 (
b111 &
#1840000
0"
0;
0:
1-
12
07
b0 *
06
b11 !
b11 )
0<
0/
04
09
1>
b1000 $
b1000 (
b1000 &
#1850000
b10 !
b10 )
0-
1/
b1001 $
b1001 (
b1001 &
#1860000
1-
b1 !
b1 )
02
0/
14
b1010 $
b1010 (
b1010 &
#1870000
b0 !
b0 )
0-
1/
b1011 $
b1011 (
b1011 &
#1880000
1"
1;
1<
1:
1-
12
b1111 !
b1111 )
17
b11000 *
16
0/
04
19
b1100 $
b1100 (
b1100 &
#1890000
b1110 !
b1110 )
0-
1/
b1101 $
b1101 (
b1101 &
#1900000
1-
b1101 !
b1101 )
02
0/
14
b1110 $
b1110 (
b1110 &
#1910000
b1100 !
b1100 )
0-
1/
b1111 $
b1111 (
b1111 &
#1920000
0"
0;
0:
b0 *
06
b1100 !
b1100 )
1<
0/
04
09
0>
0.
03
18
b0 $
b0 (
b1100 #
b1100 '
b1100 %
b0 &
#1930000
07
15
11
12
10
b1011 !
b1011 )
1-
b110 *
1,
1/
b1 $
b1 (
b1 &
#1940000
00
0-
b100 *
0,
b1010 !
b1010 )
12
0/
14
b10 $
b10 (
b10 &
#1950000
02
10
b1001 !
b1001 )
1-
b110 *
1,
1/
b11 $
b11 (
b11 &
#1960000
1<
0:
06
00
05
0-
0,
02
b0 *
01
b1000 !
b1000 )
07
0/
04
19
b100 $
b100 (
b100 &
#1970000
0<
1:
16
17
15
11
12
10
b111 !
b111 )
1-
b1110 *
1,
1/
b101 $
b101 (
b101 &
#1980000
00
0-
b1100 *
0,
b110 !
b110 )
12
0/
14
b110 $
b110 (
b110 &
#1990000
02
10
b101 !
b101 )
1-
b1110 *
1,
1/
b111 $
b111 (
b111 &
#2000000
0:
0"
06
0;
00
05
0-
0,
02
b0 *
01
17
b100 !
b100 )
0<
0/
04
09
1>
b1000 $
b1000 (
b1000 &
#2010000
07
15
11
12
10
b11 !
b11 )
1-
b110 *
1,
1/
b1001 $
b1001 (
b1001 &
#2020000
00
0-
b100 *
0,
b10 !
b10 )
12
0/
14
b1010 $
b1010 (
b1010 &
#2030000
02
10
b1 !
b1 )
1-
b110 *
1,
1/
b1011 $
b1011 (
b1011 &
#2040000
0"
0;
0<
0:
06
00
05
0-
0,
02
b0 *
01
b0 !
b0 )
07
0/
04
19
b1100 $
b1100 (
b1100 &
#2050000
1"
1;
1<
1:
16
17
15
11
12
10
b1111 !
b1111 )
1-
b11110 *
1,
1/
b1101 $
b1101 (
b1101 &
#2060000
00
0-
b11100 *
0,
b1110 !
b1110 )
12
0/
14
b1110 $
b1110 (
b1110 &
#2070000
02
10
b1101 !
b1101 )
1-
b11110 *
1,
1/
b1111 $
b1111 (
b1111 &
#2080000
0:
0"
06
0;
00
05
0,
02
b0 *
01
17
b1101 !
b1101 )
1<
0/
04
09
0>
1.
b0 $
b0 (
b1101 #
b1101 '
b1101 %
b0 &
#2090000
b1100 !
b1100 )
0-
1/
b1 $
b1 (
b1 &
#2100000
07
15
1-
b1011 !
b1011 )
12
b100 *
11
0/
14
b10 $
b10 (
b10 &
#2110000
b1010 !
b1010 )
0-
1/
b11 $
b11 (
b11 &
#2120000
1<
0:
06
05
1-
02
b0 *
01
b1001 !
b1001 )
07
0/
04
19
b100 $
b100 (
b100 &
#2130000
b1000 !
b1000 )
0-
1/
b101 $
b101 (
b101 &
#2140000
0<
1:
16
17
15
1-
b111 !
b111 )
12
b1100 *
11
0/
14
b110 $
b110 (
b110 &
#2150000
b110 !
b110 )
0-
1/
b111 $
b111 (
b111 &
#2160000
0:
0"
06
0;
05
1-
02
b0 *
01
17
b101 !
b101 )
0<
0/
04
09
1>
b1000 $
b1000 (
b1000 &
#2170000
b100 !
b100 )
0-
1/
b1001 $
b1001 (
b1001 &
#2180000
07
15
1-
b11 !
b11 )
12
b100 *
11
0/
14
b1010 $
b1010 (
b1010 &
#2190000
b10 !
b10 )
0-
1/
b1011 $
b1011 (
b1011 &
#2200000
0"
0;
0<
0:
06
05
1-
02
b0 *
01
b1 !
b1 )
07
0/
04
19
b1100 $
b1100 (
b1100 &
#2210000
b0 !
b0 )
0-
1/
b1101 $
b1101 (
b1101 &
#2220000
1"
1;
1<
1:
16
17
15
1-
b1111 !
b1111 )
12
b11100 *
11
0/
14
b1110 $
b1110 (
b1110 &
#2230000
b1110 !
b1110 )
0-
1/
b1111 $
b1111 (
b1111 &
#2240000
0:
0"
06
0;
05
b0 *
01
17
b1110 !
b1110 )
1<
0/
04
09
0>
0.
13
b0 $
b0 (
b1110 #
b1110 '
b1110 %
b0 &
#2250000
02
10
b1101 !
b1101 )
1-
b10 *
1,
1/
b1 $
b1 (
b1 &
#2260000
17
05
01
00
0-
b0 *
0,
b1100 !
b1100 )
02
0/
14
b10 $
b10 (
b10 &
#2270000
07
15
11
12
10
b1011 !
b1011 )
1-
b110 *
1,
1/
b11 $
b11 (
b11 &
#2280000
1<
05
0:
01
06
00
0-
b0 *
0,
12
b1010 !
b1010 )
07
0/
04
19
b100 $
b100 (
b100 &
#2290000
02
10
b1001 !
b1001 )
1-
b10 *
1,
1/
b101 $
b101 (
b101 &
#2300000
1<
0:
06
07
05
01
00
0-
b0 *
0,
b1000 !
b1000 )
02
0/
14
b110 $
b110 (
b110 &
#2310000
0<
1:
16
17
15
11
12
10
b111 !
b111 )
1-
b1110 *
1,
1/
b111 $
b111 (
b111 &
#2320000
05
0:
0"
01
06
0;
00
0-
b0 *
0,
12
17
b110 !
b110 )
0<
0/
04
09
1>
b1000 $
b1000 (
b1000 &
#2330000
02
10
b101 !
b101 )
1-
b10 *
1,
1/
b1001 $
b1001 (
b1001 &
#2340000
17
05
01
00
0-
b0 *
0,
b100 !
b100 )
02
0/
14
b1010 $
b1010 (
b1010 &
#2350000
07
15
11
12
10
b11 !
b11 )
1-
b110 *
1,
1/
b1011 $
b1011 (
b1011 &
#2360000
0"
0;
0<
05
0:
01
06
00
0-
b0 *
0,
12
b10 !
b10 )
07
0/
04
19
b1100 $
b1100 (
b1100 &
#2370000
02
10
b1 !
b1 )
1-
b10 *
1,
1/
b1101 $
b1101 (
b1101 &
#2380000
0"
0;
0<
0:
06
07
05
01
00
0-
b0 *
0,
b0 !
b0 )
02
0/
14
b1110 $
b1110 (
b1110 &
#2390000
1"
1;
1<
1:
16
17
15
11
12
10
b1111 !
b1111 )
1-
b11110 *
1,
1/
b1111 $
b1111 (
b1111 &
