LearnBasics/Multiplexer_8_1/Multiplexer_8_1.v
module Multiplexer_8_1 (
    input [7:0] in,
    input [2:0] select,
    output reg out
);

always @(*) begin
    case(select)
        3'b000: out = in[0];
        3'b001: out = in[1];
        3'b010: out = in[2];
        3'b011: out = in[3];
        3'b100: out = in[4];
        3'b101: out = in[5];
        3'b110: out = in[6];
        3'b111: out = in[7];
        default: out = 1'bx;
    endcase
end

endmodule

LearnBasics/Multiplexer_8_1/Multiplexer_8_1_tb.v
`timescale 1ns/1ps
module Multiplexer_8_1_tb;

    reg [7:0] in;
    reg [2:0] select;
    wire out;

    Multiplexer_8_1 mux (
        .in(in),
        .select(select),
        .out(out)
    );

    initial begin
        $dumpfile("wave.vcd");
        $dumpvars(0, Multiplexer_8_1_tb);
    end

    initial begin
        $monitor ("Time=%0t in=%b select=%b out=%b",
                    $time, in, select, out);
            in = 8'b10101010;
            select = 0; #10;
            select = 1; #10;
            select = 2; #10;
            select = 3; #10;
            select = 4; #10;
            select = 5; #10;
            select = 6; #10;
            select = 7; #10;

        $finish;

    end

endmodule

LearnBasics/Multiplexer_8_1/wave.vcd
$date
	Tue Jul 28 17:01:47 2026
$end
$version
	Icarus Verilog
$end
$timescale
	1ps
$end
$scope module Multiplexer_8_1_tb $end
$var wire 1 ! out $end
$var reg 8 " in [7:0] $end
$var reg 3 # select [2:0] $end
$scope module mux $end
$var wire 8 $ in [7:0] $end
$var wire 3 % select [2:0] $end
$var reg 1 ! out $end
$upscope $end
$upscope $end
$enddefinitions $end
#0
$dumpvars
b0 %
b10101010 $
b0 #
b10101010 "
0!
$end
#10000
1!
b1 #
b1 %
#20000
0!
b10 #
b10 %
#30000
1!
b11 #
b11 %
#40000
0!
b100 #
b100 %
#50000
1!
b101 #
b101 %
#60000
0!
b110 #
b110 %
#70000
1!
b111 #
b111 %
