LearnBasics/ALU_top/Ripple_Carry_Adder/Full_adder.v
module Full_adder (
    input a, b, cin,
    output s, cout
);
    assign s = a ^ b ^ cin;
    assign cout = (a & b) | (a & cin) | (b & cin);

endmodule

LearnBasics/ALU_top/Ripple_Carry_Adder/Ripple_Carry_Adder.v
module Ripple_Carry_Adder (
    input [3:0] a,
    input [3:0] b,
    output [3:0] s,
    output cout
);
    wire [4:0] c;
    assign c[0] = 1'b0;

    Full_adder F0 (
        .a(a[0]),
        .b(b[0]),
        .cin(c[0]),
        .s(s[0]),
        .cout(c[1])
    );

    Full_adder F1 (
        .a(a[1]),
        .b(b[1]),
        .cin(c[1]),
        .s(s[1]),
        .cout(c[2])
    );
    
    Full_adder F2 (
        .a(a[2]),
        .b(b[2]),
        .cin(c[2]),
        .s(s[2]),
        .cout(c[3])
    );

    Full_adder F3 (
        .a(a[3]),
        .b(b[3]),
        .cin(c[3]),
        .s(s[3]),
        .cout(c[4])
    );

    assign cout = c[4];

endmodule

LearnBasics/ALU_top/Ripple_Carry_Adder/tb_RCA.v
`timescale 1ns/1ps

module tb_RCA;

    reg [3:0] a;
    reg [3:0] b;
    wire [3:0] s;
    wire cout;
    //wire [4:0] c;

    Ripple_Carry_Adder uut(
        .a(a),
        .b(b),
        //.c(c),
        .s(s),
        .cout(cout)
    );

    initial begin
        $dumpfile("wave.vcd");
        $dumpvars(0, uut);
    end

    integer i, j;
    initial begin
        $monitor("Time=%0t a=%b b=%b s=%b cout=%b",
                    $time, a, b, s, cout);
                    
            for (i = 0; i < 16; i = i + 1) begin
                for (j = 0; j < 16; j = j + 1) begin
                    a = i;
                    b = j;
                    #10;
                end
            end

        $finish;

    end

endmodule

LearnBasics/ALU_top/Ripple_Carry_Adder/wave.vcd
$date
	Thu Jul 30 17:03:16 2026
$end
$version
	Icarus Verilog
$end
$timescale
	1ps
$end
$scope module tb_RCA $end
$scope module uut $end
$var wire 4 ! a [3:0] $end
$var wire 4 " b [3:0] $end
$var wire 4 # s [3:0] $end
$var wire 1 $ cout $end
$var wire 5 % c [4:0] $end
$scope module F0 $end
$var wire 1 & a $end
$var wire 1 ' b $end
$var wire 1 ( cin $end
$var wire 1 ) cout $end
$var wire 1 * s $end
$upscope $end
$scope module F1 $end
$var wire 1 + a $end
$var wire 1 , b $end
$var wire 1 - cin $end
$var wire 1 . cout $end
$var wire 1 / s $end
$upscope $end
$scope module F2 $end
$var wire 1 0 a $end
$var wire 1 1 b $end
$var wire 1 2 cin $end
$var wire 1 3 cout $end
$var wire 1 4 s $end
$upscope $end
$scope module F3 $end
$var wire 1 5 a $end
$var wire 1 6 b $end
$var wire 1 7 cin $end
$var wire 1 8 cout $end
$var wire 1 9 s $end
$upscope $end
$upscope $end
$upscope $end
$enddefinitions $end
#0
$dumpvars
09
08
07
06
05
04
03
02
01
00
0/
0.
0-
0,
0+
0*
0)
0(
0'
0&
b0 %
0$
b0 #
b0 "
b0 !
$end
#10000
b1 #
1*
1'
b1 "
#20000
0*
b10 #
1/
0'
1,
b10 "
#30000
b11 #
1*
1'
b11 "
#40000
0*
0/
b100 #
14
0'
0,
11
b100 "
#50000
b101 #
1*
1'
b101 "
#60000
0*
b110 #
1/
0'
1,
b110 "
#70000
b111 #
1*
1'
b111 "
#80000
0*
0/
04
b1000 #
19
0'
0,
01
16
b1000 "
#90000
b1001 #
1*
1'
b1001 "
#100000
0*
b1010 #
1/
0'
1,
b1010 "
#110000
b1011 #
1*
1'
b1011 "
#120000
0*
0/
b1100 #
14
0'
0,
11
b1100 "
#130000
b1101 #
1*
1'
b1101 "
#140000
0*
b1110 #
1/
0'
1,
b1110 "
#150000
b1111 #
1*
1'
b1111 "
#160000
0/
04
b1 #
09
0'
0,
01
06
1&
b0 "
b1 !
#170000
1/
1-
b10 %
1)
b10 #
0*
1'
b1 "
#180000
0-
04
0)
02
1*
b11 #
1/
b0 %
0.
0'
1,
b10 "
#190000
14
12
1.
0/
1-
b110 %
1)
b100 #
0*
1'
b11 "
#200000
0-
09
0)
02
07
1*
0/
0.
b101 #
14
b0 %
03
0'
0,
11
b100 "
#210000
1/
1-
b10 %
1)
b110 #
0*
1'
b101 "
#220000
09
07
03
0-
14
0)
02
1*
b111 #
1/
b0 %
0.
0'
1,
b110 "
#230000
19
17
13
04
12
1.
0/
1-
b1110 %
1)
b1000 #
0*
1'
b111 "
#240000
0-
0)
02
07
0$
1*
0/
0.
04
03
b1001 #
19
b0 %
08
0'
0,
01
16
b1000 "
#250000
1/
1-
b10 %
1)
b1010 #
0*
1'
b1001 "
#260000
0-
04
0)
02
1*
b1011 #
1/
b0 %
0.
0'
1,
b1010 "
#270000
14
12
1.
0/
1-
b110 %
1)
b1100 #
0*
1'
b1011 "
#280000
0$
08
0-
19
0)
02
07
1*
0/
0.
b1101 #
14
b0 %
03
0'
0,
11
b1100 "
#290000
1/
1-
b10 %
1)
b1110 #
0*
1'
b1101 "
#300000
0$
08
19
07
03
0-
14
0)
02
1*
b1111 #
1/
b0 %
0.
0'
1,
b1110 "
#310000
1$
18
09
17
13
04
12
1.
0/
1-
b11110 %
1)
b0 #
0*
1'
b1111 "
#320000
02
0.
1/
0-
07
0$
0)
04
03
b10 #
09
b0 %
08
0'
0,
01
06
0&
1+
b0 "
b10 !
#330000
b11 #
1*
1'
b1 "
#340000
14
12
b100 %
1.
0*
b100 #
0/
0'
1,
b10 "
#350000
b101 #
1*
1'
b11 "
#360000
02
09
0.
07
0*
1/
b110 #
14
b0 %
03
0'
0,
11
b100 "
#370000
b111 #
1*
1'
b101 "
#380000
19
17
13
04
12
b1100 %
1.
0*
b1000 #
0/
0'
1,
b110 "
#390000
b1001 #
1*
1'
b111 "
#400000
02
0.
07
0$
0*
1/
04
03
b1010 #
19
b0 %
08
0'
0,
01
16
b1000 "
#410000
b1011 #
1*
1'
b1001 "
#420000
14
12
b100 %
1.
0*
b1100 #
0/
0'
1,
b1010 "
#430000
b1101 #
1*
1'
b1011 "
#440000
0$
08
02
19
0.
07
0*
1/
b1110 #
14
b0 %
03
0'
0,
11
b1100 "
#450000
b1111 #
1*
1'
b1101 "
#460000
1$
18
09
17
13
04
12
b11100 %
1.
0*
b0 #
0/
0'
1,
b1110 "
#470000
b1 #
1*
1'
b1111 "
#480000
02
0.
07
0$
1/
04
03
b11 #
09
b0 %
08
0'
0,
01
06
1&
b0 "
b11 !
#490000
14
12
1.
0/
1-
b110 %
1)
b100 #
0*
1'
b1 "
#500000
0-
b100 %
0)
1*
b101 #
0/
0'
1,
b10 "
#510000
1/
1-
b110 %
1)
b110 #
0*
1'
b11 "
#520000
02
0.
0-
09
0)
07
1*
1/
b111 #
14
b0 %
03
0'
0,
11
b100 "
#530000
19
17
13
04
12
1.
0/
1-
b1110 %
1)
b1000 #
0*
1'
b101 "
#540000
0-
b1100 %
0)
1*
b1001 #
0/
0'
1,
b110 "
#550000
1/
1-
b1110 %
1)
b1010 #
0*
1'
b111 "
#560000
02
0.
0-
0)
07
0$
1*
1/
04
03
b1011 #
19
b0 %
08
0'
0,
01
16
b1000 "
#570000
14
12
1.
0/
1-
b110 %
1)
b1100 #
0*
1'
b1001 "
#580000
0-
b100 %
0)
1*
b1101 #
0/
0'
1,
b1010 "
#590000
1/
1-
b110 %
1)
b1110 #
0*
1'
b1011 "
#600000
02
0.
0$
08
0-
19
0)
07
1*
1/
b1111 #
14
b0 %
03
0'
0,
11
b1100 "
#610000
1$
18
09
17
13
04
12
1.
0/
1-
b11110 %
1)
b0 #
0*
1'
b1101 "
#620000
0-
b11100 %
0)
1*
b1 #
0/
0'
1,
b1110 "
#630000
1/
1-
b11110 %
1)
b10 #
0*
1'
b1111 "
#640000
07
03
0/
14
0-
02
0$
0)
0.
b100 #
09
b0 %
08
0'
0,
01
06
0&
0+
10
b0 "
b100 !
#650000
b101 #
1*
1'
b1 "
#660000
0*
b110 #
1/
0'
1,
b10 "
#670000
b111 #
1*
1'
b11 "
#680000
19
17
b1000 %
13
0*
0/
b1000 #
04
0'
0,
11
b100 "
#690000
b1001 #
1*
1'
b101 "
#700000
0*
b1010 #
1/
0'
1,
b110 "
#710000
b1011 #
1*
1'
b111 "
#720000
07
03
0$
0*
0/
14
b1100 #
19
b0 %
08
0'
0,
01
16
b1000 "
#730000
b1101 #
1*
1'
b1001 "
#740000
0*
b1110 #
1/
0'
1,
b1010 "
#750000
b1111 #
1*
1'
b1011 "
#760000
1$
18
09
17
b11000 %
13
0*
0/
b0 #
04
0'
0,
11
b1100 "
#770000
b1 #
1*
1'
b1101 "
#780000
0*
b10 #
1/
0'
1,
b1110 "
#790000
b11 #
1*
1'
b1111 "
#800000
07
03
0$
0/
14
b101 #
09
b0 %
08
0'
0,
01
06
1&
b0 "
b101 !
#810000
1/
1-
b10 %
1)
b110 #
0*
1'
b1 "
#820000
09
07
03
0-
14
0)
02
1*
b111 #
1/
b0 %
0.
0'
1,
b10 "
#830000
19
17
13
04
12
1.
0/
1-
b1110 %
1)
b1000 #
0*
1'
b11 "
#840000
0-
0)
02
1*
0/
b1000 %
0.
b1001 #
04
0'
0,
11
b100 "
#850000
1/
1-
b1010 %
1)
b1010 #
0*
1'
b101 "
#860000
0-
04
0)
02
1*
b1011 #
1/
b1000 %
0.
0'
1,
b110 "
#870000
14
12
1.
0/
1-
b1110 %
1)
b1100 #
0*
1'
b111 "
#880000
07
03
0-
0)
02
0$
1*
0/
0.
14
b1101 #
19
b0 %
08
0'
0,
01
16
b1000 "
#890000
1/
1-
b10 %
1)
b1110 #
0*
1'
b1001 "
#900000
0$
08
19
07
03
0-
14
0)
02
1*
b1111 #
1/
b0 %
0.
0'
1,
b1010 "
#910000
1$
18
09
17
13
04
12
1.
0/
1-
b11110 %
1)
b0 #
0*
1'
b1011 "
#920000
0-
0)
02
1*
0/
b11000 %
0.
b1 #
04
0'
0,
11
b1100 "
#930000
1/
1-
b11010 %
1)
b10 #
0*
1'
b1101 "
#940000
0-
04
0)
02
1*
b11 #
1/
b11000 %
0.
0'
1,
b1110 "
#950000
14
12
1.
0/
1-
b11110 %
1)
b100 #
0*
1'
b1111 "
#960000
07
03
02
0.
1/
0-
0$
0)
14
b110 #
09
b0 %
08
0'
0,
01
06
0&
1+
b0 "
b110 !
#970000
b111 #
1*
1'
b1 "
#980000
19
17
13
04
12
b1100 %
1.
0*
b1000 #
0/
0'
1,
b10 "
#990000
b1001 #
1*
1'
b11 "
#1000000
02
b1000 %
0.
0*
1/
b1010 #
04
0'
0,
11
b100 "
#1010000
b1011 #
1*
1'
b101 "
#1020000
14
12
b1100 %
1.
0*
b1100 #
0/
0'
1,
b110 "
#1030000
b1101 #
1*
1'
b111 "
#1040000
07
03
02
0.
0$
0*
1/
14
b1110 #
19
b0 %
08
0'
0,
01
16
b1000 "
#1050000
b1111 #
1*
1'
b1001 "
#1060000
1$
18
09
17
13
04
12
b11100 %
1.
0*
b0 #
0/
0'
1,
b1010 "
#1070000
b1 #
1*
1'
b1011 "
#1080000
02
b11000 %
0.
0*
1/
b10 #
04
0'
0,
11
b1100 "
#1090000
b11 #
1*
1'
b1101 "
#1100000
14
12
b11100 %
1.
0*
b100 #
0/
0'
1,
b1110 "
#1110000
b101 #
1*
1'
b1111 "
#1120000
07
03
02
0.
0$
1/
14
b111 #
09
b0 %
08
0'
0,
01
06
1&
b0 "
b111 !
#1130000
19
17
13
04
12
1.
0/
1-
b1110 %
1)
b1000 #
0*
1'
b1 "
#1140000
0-
b1100 %
0)
1*
b1001 #
0/
0'
1,
b10 "
#1150000
1/
1-
b1110 %
1)
b1010 #
0*
1'
b11 "
#1160000
02
0.
0-
b1000 %
0)
1*
1/
b1011 #
04
0'
0,
11
b100 "
#1170000
14
12
1.
0/
1-
b1110 %
1)
b1100 #
0*
1'
b101 "
#1180000
0-
b1100 %
0)
1*
b1101 #
0/
0'
1,
b110 "
#1190000
1/
1-
b1110 %
1)
b1110 #
0*
1'
b111 "
#1200000
07
03
02
0.
0-
0)
0$
1*
1/
14
b1111 #
19
b0 %
08
0'
0,
01
16
b1000 "
#1210000
1$
18
09
17
13
04
12
1.
0/
1-
b11110 %
1)
b0 #
0*
1'
b1001 "
#1220000
0-
b11100 %
0)
1*
b1 #
0/
0'
1,
b1010 "
#1230000
1/
1-
b11110 %
1)
b10 #
0*
1'
b1011 "
#1240000
02
0.
0-
b11000 %
0)
1*
1/
b11 #
04
0'
0,
11
b1100 "
#1250000
14
12
1.
0/
1-
b11110 %
1)
b100 #
0*
1'
b1101 "
#1260000
0-
b11100 %
0)
1*
b101 #
0/
0'
1,
b1110 "
#1270000
1/
1-
b11110 %
1)
b110 #
0*
1'
b1111 "
#1280000
0$
08
0/
04
b1000 #
19
0-
02
07
0)
0.
b0 %
03
0'
0,
01
06
0&
0+
00
15
b0 "
b1000 !
#1290000
b1001 #
1*
1'
b1 "
#1300000
0*
b1010 #
1/
0'
1,
b10 "
#1310000
b1011 #
1*
1'
b11 "
#1320000
0*
0/
b1100 #
14
0'
0,
11
b100 "
#1330000
b1101 #
1*
1'
b101 "
#1340000
0*
b1110 #
1/
0'
1,
b110 "
#1350000
b1111 #
1*
1'
b111 "
#1360000
1$
b10000 %
18
0*
0/
04
b0 #
09
0'
0,
01
16
b1000 "
#1370000
b1 #
1*
1'
b1001 "
#1380000
0*
b10 #
1/
0'
1,
b1010 "
#1390000
b11 #
1*
1'
b1011 "
#1400000
0*
0/
b100 #
14
0'
0,
11
b1100 "
#1410000
b101 #
1*
1'
b1101 "
#1420000
0*
b110 #
1/
0'
1,
b1110 "
#1430000
b111 #
1*
1'
b1111 "
#1440000
0$
b0 %
08
0/
04
b1001 #
19
0'
0,
01
06
1&
b0 "
b1001 !
#1450000
1/
1-
b10 %
1)
b1010 #
0*
1'
b1 "
#1460000
0-
04
0)
02
1*
b1011 #
1/
b0 %
0.
0'
1,
b10 "
#1470000
14
12
1.
0/
1-
b110 %
1)
b1100 #
0*
1'
b11 "
#1480000
0$
08
0-
19
0)
02
07
1*
0/
0.
b1101 #
14
b0 %
03
0'
0,
11
b100 "
#1490000
1/
1-
b10 %
1)
b1110 #
0*
1'
b101 "
#1500000
0$
08
19
07
03
0-
14
0)
02
1*
b1111 #
1/
b0 %
0.
0'
1,
b110 "
#1510000
1$
18
09
17
13
04
12
1.
0/
1-
b11110 %
1)
b0 #
0*
1'
b111 "
#1520000
0-
0)
02
07
1*
0/
0.
04
b10000 %
03
b1 #
09
0'
0,
01
16
b1000 "
#1530000
1/
1-
b10010 %
1)
b10 #
0*
1'
b1001 "
#1540000
0-
04
0)
02
1*
b11 #
1/
b10000 %
0.
0'
1,
b1010 "
#1550000
14
12
1.
0/
1-
b10110 %
1)
b100 #
0*
1'
b1011 "
#1560000
0-
09
0)
02
07
1*
0/
0.
b101 #
14
b10000 %
03
0'
0,
11
b1100 "
#1570000
1/
1-
b10010 %
1)
b110 #
0*
1'
b1101 "
#1580000
09
07
03
0-
14
0)
02
1*
b111 #
1/
b10000 %
0.
0'
1,
b1110 "
#1590000
19
17
13
04
12
1.
0/
1-
b11110 %
1)
b1000 #
0*
1'
b1111 "
#1600000
02
0$
0.
08
1/
0-
07
0)
04
b0 %
03
b1010 #
19
0'
0,
01
06
0&
1+
b0 "
b1010 !
#1610000
b1011 #
1*
1'
b1 "
#1620000
14
12
b100 %
1.
0*
b1100 #
0/
0'
1,
b10 "
#1630000
b1101 #
1*
1'
b11 "
#1640000
0$
08
02
19
0.
07
0*
1/
b1110 #
14
b0 %
03
0'
0,
11
b100 "
#1650000
b1111 #
1*
1'
b101 "
#1660000
1$
18
09
17
13
04
12
b11100 %
1.
0*
b0 #
0/
0'
1,
b110 "
#1670000
b1 #
1*
1'
b111 "
#1680000
02
0.
07
0*
1/
04
b10000 %
03
b10 #
09
0'
0,
01
16
b1000 "
#1690000
b11 #
1*
1'
b1001 "
#1700000
14
12
b10100 %
1.
0*
b100 #
0/
0'
1,
b1010 "
#1710000
b101 #
1*
1'
b1011 "
#1720000
02
09
0.
07
0*
1/
b110 #
14
b10000 %
03
0'
0,
11
b1100 "
#1730000
b111 #
1*
1'
b1101 "
#1740000
19
17
13
04
12
b11100 %
1.
0*
b1000 #
0/
0'
1,
b1110 "
#1750000
b1001 #
1*
1'
b1111 "
#1760000
0$
08
02
0.
07
1/
04
b0 %
03
b1011 #
19
0'
0,
01
06
1&
b0 "
b1011 !
#1770000
14
12
1.
0/
1-
b110 %
1)
b1100 #
0*
1'
b1 "
#1780000
0-
b100 %
0)
1*
b1101 #
0/
0'
1,
b10 "
#1790000
1/
1-
b110 %
1)
b1110 #
0*
1'
b11 "
#1800000
02
0.
0$
08
0-
19
0)
07
1*
1/
b1111 #
14
b0 %
03
0'
0,
11
b100 "
#1810000
1$
18
09
17
13
04
12
1.
0/
1-
b11110 %
1)
b0 #
0*
1'
b101 "
#1820000
0-
b11100 %
0)
1*
b1 #
0/
0'
1,
b110 "
#1830000
1/
1-
b11110 %
1)
b10 #
0*
1'
b111 "
#1840000
02
0.
0-
0)
07
1*
1/
04
b10000 %
03
b11 #
09
0'
0,
01
16
b1000 "
#1850000
14
12
1.
0/
1-
b10110 %
1)
b100 #
0*
1'
b1001 "
#1860000
0-
b10100 %
0)
1*
b101 #
0/
0'
1,
b1010 "
#1870000
1/
1-
b10110 %
1)
b110 #
0*
1'
b1011 "
#1880000
02
0.
0-
09
0)
07
1*
1/
b111 #
14
b10000 %
03
0'
0,
11
b1100 "
#1890000
19
17
13
04
12
1.
0/
1-
b11110 %
1)
b1000 #
0*
1'
b1101 "
#1900000
0-
b11100 %
0)
1*
b1001 #
0/
0'
1,
b1110 "
#1910000
1/
1-
b11110 %
1)
b1010 #
0*
1'
b1111 "
#1920000
0$
08
07
03
0/
14
0-
02
0)
b0 %
0.
b1100 #
19
0'
0,
01
06
0&
0+
10
b0 "
b1100 !
#1930000
b1101 #
1*
1'
b1 "
#1940000
0*
b1110 #
1/
0'
1,
b10 "
#1950000
b1111 #
1*
1'
b11 "
#1960000
1$
18
09
17
b11000 %
13
0*
0/
b0 #
04
0'
0,
11
b100 "
#1970000
b1 #
1*
1'
b101 "
#1980000
0*
b10 #
1/
0'
1,
b110 "
#1990000
b11 #
1*
1'
b111 "
#2000000
07
b10000 %
03
0*
0/
14
b100 #
09
0'
0,
01
16
b1000 "
#2010000
b101 #
1*
1'
b1001 "
#2020000
0*
b110 #
1/
0'
1,
b1010 "
#2030000
b111 #
1*
1'
b1011 "
#2040000
19
17
b11000 %
13
0*
0/
b1000 #
04
0'
0,
11
b1100 "
#2050000
b1001 #
1*
1'
b1101 "
#2060000
0*
b1010 #
1/
0'
1,
b1110 "
#2070000
b1011 #
1*
1'
b1111 "
#2080000
0$
08
07
b0 %
03
0/
14
b1101 #
19
0'
0,
01
06
1&
b0 "
b1101 !
#2090000
1/
1-
b10 %
1)
b1110 #
0*
1'
b1 "
#2100000
0$
08
19
07
03
0-
14
0)
02
1*
b1111 #
1/
b0 %
0.
0'
1,
b10 "
#2110000
1$
18
09
17
13
04
12
1.
0/
1-
b11110 %
1)
b0 #
0*
1'
b11 "
#2120000
0-
0)
02
1*
0/
b11000 %
0.
b1 #
04
0'
0,
11
b100 "
#2130000
1/
1-
b11010 %
1)
b10 #
0*
1'
b101 "
#2140000
0-
04
0)
02
1*
b11 #
1/
b11000 %
0.
0'
1,
b110 "
#2150000
14
12
1.
0/
1-
b11110 %
1)
b100 #
0*
1'
b111 "
#2160000
07
03
0-
0)
02
1*
0/
b10000 %
0.
14
b101 #
09
0'
0,
01
16
b1000 "
#2170000
1/
1-
b10010 %
1)
b110 #
0*
1'
b1001 "
#2180000
09
07
03
0-
14
0)
02
1*
b111 #
1/
b10000 %
0.
0'
1,
b1010 "
#2190000
19
17
13
04
12
1.
0/
1-
b11110 %
1)
b1000 #
0*
1'
b1011 "
#2200000
0-
0)
02
1*
0/
b11000 %
0.
b1001 #
04
0'
0,
11
b1100 "
#2210000
1/
1-
b11010 %
1)
b1010 #
0*
1'
b1101 "
#2220000
0-
04
0)
02
1*
b1011 #
1/
b11000 %
0.
0'
1,
b1110 "
#2230000
14
12
1.
0/
1-
b11110 %
1)
b1100 #
0*
1'
b1111 "
#2240000
0$
08
07
03
02
0.
1/
0-
b0 %
0)
14
b1110 #
19
0'
0,
01
06
0&
1+
b0 "
b1110 !
#2250000
b1111 #
1*
1'
b1 "
#2260000
1$
18
09
17
13
04
12
b11100 %
1.
0*
b0 #
0/
0'
1,
b10 "
#2270000
b1 #
1*
1'
b11 "
#2280000
02
b11000 %
0.
0*
1/
b10 #
04
0'
0,
11
b100 "
#2290000
b11 #
1*
1'
b101 "
#2300000
14
12
b11100 %
1.
0*
b100 #
0/
0'
1,
b110 "
#2310000
b101 #
1*
1'
b111 "
#2320000
07
03
02
b10000 %
0.
0*
1/
14
b110 #
09
0'
0,
01
16
b1000 "
#2330000
b111 #
1*
1'
b1001 "
#2340000
19
17
13
04
12
b11100 %
1.
0*
b1000 #
0/
0'
1,
b1010 "
#2350000
b1001 #
1*
1'
b1011 "
#2360000
02
b11000 %
0.
0*
1/
b1010 #
04
0'
0,
11
b1100 "
#2370000
b1011 #
1*
1'
b1101 "
#2380000
14
12
b11100 %
1.
0*
b1100 #
0/
0'
1,
b1110 "
#2390000
b1101 #
1*
1'
b1111 "
#2400000
0$
08
07
03
02
b0 %
0.
1/
14
b1111 #
19
0'
0,
01
06
1&
b0 "
b1111 !
#2410000
1$
18
09
17
13
04
12
1.
0/
1-
b11110 %
1)
b0 #
0*
1'
b1 "
#2420000
0-
b11100 %
0)
1*
b1 #
0/
0'
1,
b10 "
#2430000
1/
1-
b11110 %
1)
b10 #
0*
1'
b11 "
#2440000
02
0.
0-
b11000 %
0)
1*
1/
b11 #
04
0'
0,
11
b100 "
#2450000
14
12
1.
0/
1-
b11110 %
1)
b100 #
0*
1'
b101 "
#2460000
0-
b11100 %
0)
1*
b101 #
0/
0'
1,
b110 "
#2470000
1/
1-
b11110 %
1)
b110 #
0*
1'
b111 "
#2480000
07
03
02
0.
0-
b10000 %
0)
1*
1/
14
b111 #
09
0'
0,
01
16
b1000 "
#2490000
19
17
13
04
12
1.
0/
1-
b11110 %
1)
b1000 #
0*
1'
b1001 "
#2500000
0-
b11100 %
0)
1*
b1001 #
0/
0'
1,
b1010 "
#2510000
1/
1-
b11110 %
1)
b1010 #
0*
1'
b1011 "
#2520000
02
0.
0-
b11000 %
0)
1*
1/
b1011 #
04
0'
0,
11
b1100 "
#2530000
14
12
1.
0/
1-
b11110 %
1)
b1100 #
0*
1'
b1101 "
#2540000
0-
b11100 %
0)
1*
b1101 #
0/
0'
1,
b1110 "
#2550000
1/
1-
b11110 %
1)
b1110 #
0*
1'
b1111 "
