LearnBasics/Prio_Encoder.v/Prio_Encoder_4_2.v/Prio_Encoder_4_2.v
module Prio_Encoder_4_2 (
    input [3:0] in,
    output reg [1:0] out
);

    always @ (*) begin
        casez(in)
            4'b1??? : out = 2'b11;
            4'b01?? : out = 2'b10;
            4'b001? : out = 2'b01;
            4'b0001 : out = 2'b00;
            default : out = 2'bxx;
        endcase
    end
    
endmodule

LearnBasics/Prio_Encoder.v/Prio_Encoder_4_2.v/tb_Prio_Encoder_4_2.v
`timescale 1ns/1ps

module tb_Prio_Encoder_4_2;

    reg [3:0] in;
    wire [1:0] out;

    Prio_Encoder_4_2 uut (
        .in(in),
        .out(out)
    );

    initial begin
        $dumpfile("wave.vcd");
        $dumpvars(0, uut);
    end

    integer i = 0;
    initial begin
        $monitor("Time=%0t in=%b out=%b",
                    $time, in, out);
            
            for (i = 0; i < 16; i = i + 1) begin
                in = i;
                #10;
            end

            $finish;
    end

endmodule

LearnBasics/Prio_Encoder.v/Prio_Encoder_4_2.v/wave.vcd
$date
	Wed Jul 29 16:07:14 2026
$end
$version
	Icarus Verilog
$end
$timescale
	1ps
$end
$scope module tb_Prio_Encoder_4_2 $end
$scope module uut $end
$var wire 4 ! in [3:0] $end
$var reg 2 " out [1:0] $end
$upscope $end
$upscope $end
$enddefinitions $end
#0
$dumpvars
bx "
b0 !
$end
#10000
b0 "
b1 !
#20000
b1 "
b10 !
#30000
b11 !
#40000
b10 "
b100 !
#50000
b101 !
#60000
b110 !
#70000
b111 !
#80000
b11 "
b1000 !
#90000
b1001 !
#100000
b1010 !
#110000
b1011 !
#120000
b1100 !
#130000
b1101 !
#140000
b1110 !
#150000
b1111 !
